hello_image/__init__.py
hello_image-0.0.2.dist-info/METADATA
hello_image-0.0.2.dist-info/WHEEL
hello_image-0.0.2.dist-info/top_level.txt
hello_image-0.0.2.dist-info/RECORD
